assumerole/__init__.py
assumerole/identity.py
assumerole/main.py
assumerole-0.6.2.dist-info/entry_points.txt
assumerole-0.6.2.dist-info/LICENSE
assumerole-0.6.2.dist-info/WHEEL
assumerole-0.6.2.dist-info/METADATA
assumerole-0.6.2.dist-info/RECORD
