Metadata-Version: 2.1
Name: assumerole
Version: 0.6.2
Summary: Python  utility that allows users to perform aws assume-role operation between different profiles
Home-page: https://github.com/kartikra/assumerole
License: MIT
Keywords: AWS,aws sts,assume-role
Author: Kartik Ramasubramanian
Author-email: r.kartik@berkeley.edu
Requires-Python: >=3.6.1,<4.0
Classifier: License :: OSI Approved :: MIT License
Classifier: Programming Language :: Python :: 3
Classifier: Programming Language :: Python :: 3.7
Classifier: Programming Language :: Python :: 3.8
Classifier: Programming Language :: Python :: 3.9
Classifier: Topic :: Software Development :: Build Tools
Classifier: Topic :: Software Development :: Libraries :: Python Modules
Requires-Dist: boto3 (>=1.15.1)
Project-URL: Repository, https://github.com/kartikra/assumerole
